odoo/addons/pos_hr_access_right/README.rst
odoo/addons/pos_hr_access_right/__init__.py
odoo/addons/pos_hr_access_right/__manifest__.py
odoo/addons/pos_hr_access_right/i18n/it.po
odoo/addons/pos_hr_access_right/i18n/pos_hr_access_right.pot
odoo/addons/pos_hr_access_right/models/__init__.py
odoo/addons/pos_hr_access_right/models/pos_session.py
odoo/addons/pos_hr_access_right/readme/CONFIGURE.rst
odoo/addons/pos_hr_access_right/readme/CONTRIBUTORS.rst
odoo/addons/pos_hr_access_right/readme/DESCRIPTION.rst
odoo/addons/pos_hr_access_right/readme/USAGE.rst
odoo/addons/pos_hr_access_right/static/description/icon.png
odoo/addons/pos_hr_access_right/static/description/index.html
odoo/addons/pos_hr_access_right/static/src/js/ActionpadWidget.js
odoo/addons/pos_hr_access_right/static/src/js/NumpadWidget.js
odoo/addons/pos_hr_access_right/static/src/js/TicketScreen.js
odoo/addons/pos_hr_access_right/tests/__init__.py
odoo/addons/pos_hr_access_right/tests/test_pos_hr_access_right.py
odoo_addon_pos_hr_access_right-16.0.1.0.1.2.dist-info/METADATA
odoo_addon_pos_hr_access_right-16.0.1.0.1.2.dist-info/WHEEL
odoo_addon_pos_hr_access_right-16.0.1.0.1.2.dist-info/top_level.txt
odoo_addon_pos_hr_access_right-16.0.1.0.1.2.dist-info/RECORD
