Metadata-Version: 2.1
Name: odoo-addon-pos_hr_access_right
Version: 16.0.1.0.1.2
Summary: Point of Sale HR - Extra Access Right for certain actions
Home-page: https://github.com/OCA/pos
Author: Binhex ,Odoo Community Association (OCA)
Author-email: support@odoo-community.org
License: AGPL-3
Classifier: Programming Language :: Python
Classifier: Framework :: Odoo
Classifier: Framework :: Odoo :: 16.0
Classifier: License :: OSI Approved :: GNU Affero General Public License v3
Requires-Python: >=3.10
Requires-Dist: odoo-addon-pos-access-right<16.1dev,>=16.0dev
Requires-Dist: odoo<16.1dev,>=16.0a
